[
  {
    "id": "order_1751192377846",
    "title": "Test4",
    "description": "asdfsd",
    "clientId": "1751022994556",
    "clientName": "Maximilian Meyer",
    "deadline": "2025-07-07T00:00:00.000Z",
    "costCenter": "n.V.",
    "priority": "medium",
    "status": "archived",
    "documents": [],
    "estimatedHours": 0,
    "actualHours": 0,
    "assignedTo": null,
    "notes": "",
    "createdAt": "2025-06-29T10:19:37.846Z",
    "updatedAt": "2025-06-29T10:22:51.437Z",
    "subTasks": [],
    "canEdit": false,
    "revisionRequest": {
      "description": "asdfger",
      "requestedAt": "2025-06-29T10:22:16.156Z"
    },
    "confirmationNote": "",
    "confirmationDate": "2025-06-29T10:22:42.433Z"
  },
  {
    "id": "order_1751192689613",
    "title": "Test6",
    "description": "asdf",
    "clientId": "1751022994556",
    "clientName": "Maximilian Meyer",
    "deadline": "2025-07-01T00:00:00.000Z",
    "costCenter": "n.V.",
    "priority": "medium",
    "status": "archived",
    "documents": [],
    "estimatedHours": 0,
    "actualHours": 0,
    "assignedTo": null,
    "notes": "",
    "createdAt": "2025-06-29T10:24:49.613Z",
    "updatedAt": "2025-06-29T10:26:11.403Z",
    "subTasks": [],
    "canEdit": false,
    "revisionRequest": {
      "description": "rera",
      "requestedAt": "2025-06-29T10:25:31.458Z"
    },
    "confirmationNote": "",
    "confirmationDate": "2025-06-29T10:25:55.215Z"
  },
  {
    "id": "order_1751192805780",
    "title": "wetretg",
    "description": "ohiougiutf",
    "clientId": "1751022994556",
    "clientName": "Maximilian Meyer",
    "deadline": "2025-07-01T00:00:00.000Z",
    "costCenter": "n.V.",
    "priority": "medium",
    "status": "archived",
    "documents": [],
    "estimatedHours": 0,
    "actualHours": 0,
    "assignedTo": null,
    "notes": "",
    "createdAt": "2025-06-29T10:26:45.780Z",
    "updatedAt": "2025-06-29T10:29:03.372Z",
    "subTasks": [],
    "canEdit": false,
    "confirmationNote": "",
    "confirmationDate": "2025-06-29T10:28:43.787Z"
  },
  {
    "id": "order_1751272903078",
    "title": "Auftrag 2",
    "description": "Test\n",
    "clientId": "1751272272538",
    "clientName": "Max",
    "deadline": "2025-07-07T00:00:00.000Z",
    "costCenter": "n.V.",
    "priority": "medium",
    "status": "completed",
    "documents": [
      {
        "id": "doc_1751273068362_0.9369355958204446",
        "name": "2525-Woche-11-Teil-02-Zentraluebung (1).pdf",
        "url": "blob:http://localhost:5173/bf73f2fc-064e-41bf-a9e6-7cb90562fc92",
        "uploadDate": "2025-06-30T08:44:28.362Z",
        "file": {}
      }
    ],
    "estimatedHours": 0,
    "actualHours": 0,
    "assignedTo": null,
    "notes": "Überarbeiten",
    "createdAt": "2025-06-30T08:41:43.078Z",
    "updatedAt": "2025-06-30T08:45:12.889Z",
    "subTasks": [],
    "canEdit": false,
    "confirmationNote": "",
    "confirmationDate": "2025-06-30T08:45:26.483Z"
  },
  {
    "id": "order_1751272934264",
    "title": "Test",
    "description": "test",
    "clientId": "1751272272538",
    "clientName": "Max",
    "deadline": "2025-07-07T00:00:00.000Z",
    "costCenter": "n.V.",
    "priority": "medium",
    "status": "pending",
    "documents": [],
    "estimatedHours": 0,
    "actualHours": 0,
    "assignedTo": null,
    "notes": "",
    "createdAt": "2025-06-30T08:42:14.264Z",
    "updatedAt": "2025-06-30T09:22:45.766Z",
    "subTasks": [
      {
        "id": "subtask_1751275318760_0.462858407137156",
        "orderId": "order_1751272934264",
        "title": "Bauteil 1",
        "description": "",
        "estimatedHours": 0,
        "actualHours": 0,
        "status": "in_progress",
        "assignedTo": "2",
        "notes": "",
        "documents": [],
        "createdAt": "2025-06-30T09:21:58.760Z",
        "updatedAt": "2025-06-30T09:22:43.974Z"
      },
      {
        "id": "subtask_1751275327236_0.6703936079500387",
        "orderId": "order_1751272934264",
        "title": "Bauteil 2",
        "description": "",
        "estimatedHours": 0,
        "actualHours": 0,
        "status": "in_progress",
        "assignedTo": "workshop_1751274342062",
        "notes": "",
        "documents": [],
        "createdAt": "2025-06-30T09:22:07.236Z",
        "updatedAt": "2025-06-30T09:22:45.766Z"
      }
    ],
    "canEdit": false
  },
  {
    "id": "order_1751272999990",
    "title": "Test9",
    "description": "alksdfg",
    "clientId": "1751272272538",
    "clientName": "Max",
    "deadline": "2025-07-07T00:00:00.000Z",
    "costCenter": "0",
    "priority": "medium",
    "status": "in_progress",
    "documents": [],
    "estimatedHours": 0,
    "actualHours": 0,
    "assignedTo": null,
    "notes": "Material Bestellt",
    "createdAt": "2025-06-30T08:43:19.990Z",
    "updatedAt": "2025-06-30T09:06:53.513Z",
    "subTasks": [
      {
        "id": "subtask_1751274306244_0.22655823497997263",
        "orderId": "order_1751272999990",
        "title": "Fräsen",
        "description": "",
        "estimatedHours": 3,
        "actualHours": 0,
        "status": "in_progress",
        "assignedTo": "2",
        "notes": "",
        "documents": [],
        "createdAt": "2025-06-30T09:05:06.244Z",
        "updatedAt": "2025-06-30T09:06:53.513Z"
      },
      {
        "id": "subtask_1751274394313_0.949839202061237",
        "orderId": "order_1751272999990",
        "title": "Drehen",
        "description": "Drehen der Teile",
        "estimatedHours": 1,
        "actualHours": 0,
        "status": "pending",
        "assignedTo": "workshop_1751274342062",
        "notes": "",
        "documents": [],
        "createdAt": "2025-06-30T09:06:34.313Z",
        "updatedAt": "2025-06-30T09:06:34.313Z"
      }
    ],
    "canEdit": false
  }
]